tests/__init__.py
tests/conftest.py
tests/helpers.py
tests/test_cli.py
tests/test_process.py
tests/test_protocol.py
tests/test_server.py
tox_server/__about__.py
tox_server/__init__.py
tox_server/__main__.py
tox_server/cli.py
tox_server/client.py
tox_server/exc.py
tox_server/interrupt.py
tox_server/process.py
tox_server/protocol.py
tox_server/server.py
tox_server-0.6.0.dist-info/LICENSE
tox_server-0.6.0.dist-info/METADATA
tox_server-0.6.0.dist-info/WHEEL
tox_server-0.6.0.dist-info/entry_points.txt
tox_server-0.6.0.dist-info/top_level.txt
tox_server-0.6.0.dist-info/RECORD
