Metadata-Version: 2.1
Name: tox-server
Version: 0.6.0
Summary: A mini tox server for calling tox in a loop
Home-page: https://github.com/alexrudy/tox-server
Author: Alex Rudy
Author-email: alex.rudy@gmail.com
License: UNKNOWN
Keywords: utilties tox testing
Platform: UNKNOWN
Classifier: Development Status :: 3 - Alpha
Classifier: Intended Audience :: Developers
Classifier: Environment :: Console
Classifier: License :: OSI Approved :: BSD License
Classifier: Operating System :: Unix
Classifier: Programming Language :: Python :: 3.7
Classifier: Programming Language :: Python :: 3.8
Classifier: Programming Language :: Python :: 3 :: Only
Classifier: Topic :: Utilities
Requires-Python: >=3.7, <4
Requires-Dist: click
Requires-Dist: pyzmq
Requires-Dist: tox
